Metadata-Version: 2.1
Name: elecfence
Version: 0.0.6
Summary: A electronic fence package
Home-page: https://github.com/muumlover/elecfence
Author: MUUMLOVER
Author-email: muumlover@foxmail.com
License: UNKNOWN
Project-URL: Say Thanks!, http://saythanks.io/to/example
Project-URL: Funding, https://donate.pypi.org
Project-URL: Source, https://github.com/muumlover/elecfence/
Project-URL: Bug Reports, https://github.com/muumlover/elecfence/issues
Keywords: elecfence geojson map gps
Platform: UNKNOWN
Classifier: Development Status :: 1 - Planning
Classifier: Intended Audience :: Developers
Classifier: License :: OSI Approved :: BSD License
Classifier: Operating System :: OS Independent
Classifier: Programming Language :: Python
Classifier: Programming Language :: Python :: 3
Classifier: Programming Language :: Python :: 3.4
Classifier: Programming Language :: Python :: 3.5
Classifier: Programming Language :: Python :: 3.6
Classifier: Topic :: Software Development :: Build Tools
